bel_commons/__init__.py
bel_commons/__main__.py
bel_commons/admin_model_views.py
bel_commons/application_utils.py
bel_commons/celery_utils.py
bel_commons/celery_worker.py
bel_commons/cli.py
bel_commons/config.py
bel_commons/constants.py
bel_commons/converters.py
bel_commons/database_service.py
bel_commons/explorer_toolbox.py
bel_commons/ext.py
bel_commons/forms.py
bel_commons/main_service.py
bel_commons/manager.py
bel_commons/manager_base.py
bel_commons/manager_utils.py
bel_commons/models.py
bel_commons/send_utils.py
bel_commons/tools_compat.py
bel_commons/utils.py
bel_commons/version.py
bel_commons/wsgi.py
bel_commons/core/__init__.py
bel_commons/core/flask_bio2bel.py
bel_commons/core/sqlalchemy.py
bel_commons/resources/__init__.py
bel_commons/resources/constants.py
bel_commons/resources/load_alzheimers.py
bel_commons/resources/load_experiments.py
bel_commons/resources/load_networks.py
bel_commons/resources/load_omics.py
bel_commons/static/css/c3.min.css
bel_commons/static/css/d3.parcoords.css
bel_commons/static/css/graph.css
bel_commons/static/css/legend.css
bel_commons/static/css/nav.css
bel_commons/static/img/BELcommons-square-1024.png
bel_commons/static/img/EFPIA_logo.jpg
bel_commons/static/img/PyBEL-logotype-100.png
bel_commons/static/img/PyBEL-square-100.png
bel_commons/static/img/SCAI-square-39.svg
bel_commons/static/img/aetionomy_logo.png
bel_commons/static/img/bel300x.png
bel_commons/static/img/eu_logo.png
bel_commons/static/img/hbp_logo.png
bel_commons/static/img/imi_logo.png
bel_commons/static/img/phago_logo.jpg
bel_commons/static/img/scai_logo.svg
bel_commons/static/img/dgx_tutorial/1.png
bel_commons/static/img/dgx_tutorial/2.png
bel_commons/static/img/dgx_tutorial/3.png
bel_commons/static/img/dgx_tutorial/4.png
bel_commons/static/img/gif/Explorer_example.gif
bel_commons/static/img/gif/loading.gif
bel_commons/static/js/bootstrap-confirmation.min.js
bel_commons/static/js/c3.min.js
bel_commons/static/js/d3.3.5.17.min.js
bel_commons-0.3.1.dist-info/LICENSE
bel_commons-0.3.1.dist-info/METADATA
bel_commons-0.3.1.dist-info/WHEEL
bel_commons-0.3.1.dist-info/entry_points.txt
bel_commons-0.3.1.dist-info/top_level.txt
bel_commons-0.3.1.dist-info/RECORD
