Metadata-Version: 2.1
Name: bel-commons
Version: 0.3.1
Summary: A web application exposing core PyBEL functionalities
Home-page: https://github.com/bel-commons/bel-commons
Author: Charles Tapley Hoyt
Author-email: cthoyt@gmail.com
Maintainer: Charles Tapley Hoyt
Maintainer-email: cthoyt@gmail.com
License: MIT
Download-URL: https://github.com/bel-commons/bel-commons/releases
Project-URL: Bug Tracker, https://github.com/bel-commons/bel-commons/issues
Project-URL: Source Code, https://github.com/bel-commons/bel-commons
Keywords: Biological Expression Language,BEL,Systems Biology,Networks Biology
Platform: UNKNOWN
Classifier: Development Status :: 4 - Beta
Classifier: Environment :: Console
Classifier: Intended Audience :: Developers
Classifier: Intended Audience :: Science/Research
Classifier: License :: OSI Approved :: MIT License
Classifier: Operating System :: OS Independent
Classifier: Programming Language :: Python
Classifier: Programming Language :: Python :: 3.7
Classifier: Programming Language :: Python :: 3 :: Only
Classifier: Topic :: Scientific/Engineering :: Bio-Informatics
Classifier: Topic :: Scientific/Engineering :: Chemistry
Requires-Python: >=3.7
Requires-Dist: pybel (<0.15.0,>=0.14.9)
Requires-Dist: pybel-tools (<0.9.0,>=0.8.0)
Requires-Dist: bio2bel (<0.4.0,>=0.3.0)
Requires-Dist: requests
Requires-Dist: click
Requires-Dist: tqdm
Requires-Dist: easy-config
Requires-Dist: dataclasses-json
Requires-Dist: ols-client
Requires-Dist: networkx (>=2.1)
Requires-Dist: pandas
Requires-Dist: scikit-learn
Requires-Dist: numpy
Requires-Dist: sqlalchemy
Requires-Dist: celery[redis]
Requires-Dist: psycopg2-binary
Requires-Dist: flask (>=1.0.0)
Requires-Dist: flask-bootstrap
Requires-Dist: flask-wtf
Requires-Dist: flask-security
Requires-Dist: flask-admin
Requires-Dist: flask-sqlalchemy
Requires-Dist: email-validator
Requires-Dist: werkzeug
Requires-Dist: jsonschema
Requires-Dist: flasgger
Requires-Dist: raven
Requires-Dist: gunicorn
Provides-Extra: bio2bel
Requires-Dist: bio2bel-hgnc ; extra == 'bio2bel'
Requires-Dist: bio2bel-chebi ; extra == 'bio2bel'
Requires-Dist: bio2bel-mirtarbase ; extra == 'bio2bel'
Requires-Dist: bio2bel-entrez ; extra == 'bio2bel'
Requires-Dist: bio2bel-expasy ; extra == 'bio2bel'
Requires-Dist: bio2bel-interpro ; extra == 'bio2bel'
Requires-Dist: bio2bel-go ; extra == 'bio2bel'
Provides-Extra: docs
Requires-Dist: sphinx ; extra == 'docs'
Requires-Dist: sphinx-rtd-theme ; extra == 'docs'
Requires-Dist: sphinx-click ; extra == 'docs'
Requires-Dist: sphinx-autodoc-typehints ; extra == 'docs'
